<annotation>
	<folder>images</folder>
	<filename>Japan_000338.jpg</filename>
	<size>
		<width>600</width>
		<height>600</height>
		<depth>3</depth>
	</size>
	<segmented>0</segmented>
	<object>
		<name>Manhole cover</name>
		<pose>Unspecified</pose>
		<truncated>0</truncated>
		<difficult>0</difficult>
		<bndbox>
			<xmin>184</xmin>
			<ymin>392</ymin>
			<xmax>253</xmax>
			<ymax>406</ymax>
		</bndbox>
	</object>
	<object>
		<name>Manhole cover</name>
		<pose>Unspecified</pose>
		<truncated>0</truncated>
		<difficult>0</difficult>
		<bndbox>
			<xmin>396</xmin>
			<ymin>397</ymin>
			<xmax>447</xmax>
			<ymax>411</ymax>
		</bndbox>
	</object>
	<object>
		<name>Manhole cover</name>
		<pose>Unspecified</pose>
		<truncated>0</truncated>
		<difficult>0</difficult>
		<bndbox>
			<xmin>170</xmin>
			<ymin>329</ymin>
			<xmax>214</xmax>
			<ymax>342</ymax>
		</bndbox>
	</object>
	</annotation>