<annotation>
	<folder>images</folder>
	<filename>Japan_005857.jpg</filename>
	<size>
		<width>600</width>
		<height>600</height>
		<depth>3</depth>
	</size>
	<segmented>0</segmented>
	<object>
		<name>Manhole cover</name>
		<pose>Unspecified</pose>
		<truncated>0</truncated>
		<difficult>0</difficult>
		<bndbox>
			<xmin>458</xmin>
			<ymin>489</ymin>
			<xmax>551</xmax>
			<ymax>522</ymax>
		</bndbox>
	</object>
	<object>
		<name>Pothole</name>
		<pose>Unspecified</pose>
		<truncated>0</truncated>
		<difficult>0</difficult>
		<bndbox>
			<xmin>435</xmin>
			<ymin>501</ymin>
			<xmax>559</xmax>
			<ymax>560</ymax>
		</bndbox>
	</object>
	<object>
		<name>Pothole</name>
		<pose>Unspecified</pose>
		<truncated>0</truncated>
		<difficult>0</difficult>
		<bndbox>
			<xmin>125</xmin>
			<ymin>488</ymin>
			<xmax>226</xmax>
			<ymax>543</ymax>
		</bndbox>
	</object>
</annotation>